Workbook

Sheet Raw Data
A1: MONTHLY P&L INPUTS | MONEE BANKING SEGMENT | FY2025
A2: METRIC | B2: MARKET | C2: 45658 | D2: 45689 | E2: 45717 | F2: 45748 | G2: 45778 | H2: 45809 | I2: 45839 | J2: 45870 | K2: 45901 | L2: 45931 | M2: 45962 | N2: 45992
A3: REVENUE (SGD '000)
B4: Indonesia | C4: 8200 | D4: 8450 | E4: 8700 | F4: 9100 | G4: 9400 | H4: 9800 | I4: 10200 | J4: 10600 | K4: 11000 | L4: 11400 | M4: 11900 | N4: 12400
B5: Philippines | C5: 3100 | D5: 3200 | E5: 3350 | F5: 3500 | G5: 3650 | H5: 3800 | I5: 3950 | J5: 4100 | K5: 4300 | L5: 4500 | M5: 4700 | N5: 4900
B6: Vietnam | C6: 1800 | D6: 1850 | E6: 2000 | F6: 2000 | G6: 2100 | H6: 2200 | I6: 2300 | J6: 2400 | K6: 2500 | L6: 2600 | M6: 2700 | N6: 2850
B7: Total | C7: =SUM(C4:C6) -> 13100 | D7: =SUM(D4:D6) -> 13500 | E7: =SUM(E4:E6) -> 14050 | F7: =SUM(F4:F6) -> 14600 | G7: =SUM(G4:G6) -> 15150 | H7: =SUM(H4:H6) -> 15800 | I7: =SUM(I4:I6) -> 16450 | J7: =SUM(J4:J6) -> 17100 | ... N7: =SUM(N4:N6) -> 20150
A8: OPERATING COST (SGD '000)
B9: Indonesia | C9: 5300 | D9: 5400 | E9: 5500 | F9: 5700 | G9: 5800 | H9: 6000 | I9: 6200 | J9: 6400 | K9: 6500 | L9: 6600 | M9: 6800 | N9: 7000
B10: Philippines | C10: 2100 | D10: 2150 | E10: 2200 | F10: 2300 | G10: 2350 | H10: 2450 | I10: 2500 | J10: 2600 | K10: 2700 | L10: 2800 | M10: 2900 | N10: 3000
B11: Vietnam | C11: 1300 | D11: 1320 | E11: 1350 | F11: 1400 | G11: 1450 | H11: 1500 | I11: 1550 | J11: 1600 | K11: 1650 | L11: 1700 | M11: 1750 | N11: 1820
B12: Total | C12: =SUM(C9:C11) -> 8700 | D12: =SUM(D9:D11) -> 8870 | E12: =SUM(E9:E11) -> 9050 | F12: =SUM(F9:F11) -> 9400 | G12: =SUM(G9:G11) -> 9600 | H12: =SUM(H9:H11) -> 9950 | I12: =SUM(I9:I11) -> 10250 | J12: =SUM(J9:J11) -> 10600 | ... N12: =SUM(N9:N11) -> 11820
A13: ACTIVE USERS ('000)
B14: Indonesia | C14: 4200 | D14: 4350 | E14: 4500 | F14: 4700 | G14: 4900 | H14: 5100 | I14: 5350 | J14: 5600 | K14: 5850 | L14: 6100 | M14: 6400 | N14: 6700
B15: Philippines | C15: 1850 | D15: 1920 | E15: 2000 | F15: 2100 | G15: 2200 | H15: 2300 | I15: 2420 | J15: 2550 | K15: 2680 | L15: 2820 | M15: 2970 | N15: 3130
B16: Vietnam | C16: 980 | D16: 1010 | E16: 1050 | F16: 1100 | G16: 1160 | H16: 1220 | I16: 1290 | J16: 1360 | K16: 1440 | L16: 1520 | M16: 1610 | N16: 1700
A17: NPL RATE (%)
B18: Indonesia | C18: 0.021 | D18: 0.02 | E18: 0.021 | F18: 0.022 | G18: 0.021 | H18: 0.02 | I18: 0.019 | J18: 0.019 | K18: 0.019 | L18: 0.018 | M18: 0.017 | N18: 0.017
B19: Philippines | C19: 0.028 | D19: 0.027 | E19: 0.027 | F19: 0.026 | G19: 0.025 | H19: 0.025 | I19: 0.024 | J19: 0.024 | K19: 0.023 | L19: 0.022 | M19: 0.022 | N19: 0.021
B20: Vietnam | C20: 0.032 | D20: 0.031 | E20: 0.03 | F20: 0.03 | G20: 0.029 | H20: 0.028 | I20: 0.028 | J20: 0.028 | K20: 0.027 | L20: 0.026 | M20: 0.025 | N20: 0.025

Sheet Budgets vs Actuals
A1: BUDGETS VS ACTUALS - REVENUE VARIANCE | MONEE BANKING SEGEMENT | FY2025
A2: MARKET | B2: METRIC | C2: 45658 | D2: 45689 | E2: 45717 | F2: 45748 | G2: 45778 | H2: 45809 | I2: 45839 | J2: 45870 | K2: 45901 | L2: 45931 | M2: 45962 | N2: 45992
A3: INDONESIA
B4: ACTUAL (SGD '000) | C4: ='Raw Data'!C4 -> 8200 | D4: ='Raw Data'!D4 -> 8450 | E4: ='Raw Data'!E4 -> 8700 | F4: ='Raw Data'!F4 -> 9100 | G4: ='Raw Data'!G4 -> 9400 | H4: ='Raw Data'!H4 -> 9800 | I4: ='Raw Data'!I4 -> 10200 | J4: ='Raw Data'!J4 -> 10600 | ... N4: ='Raw Data'!N4 -> 12400
B5: BUDGET (SGD '000) | C5: 8500 | D5: 8700 | E5: 8900 | F5: 9300 | G5: 9600 | H5: 10000 | I5: 10400 | J5: 10800 | K5: 11200 | L5: 11600 | M5: 12100 | N5: 12600
B6: VARIANCE (SGD '000) | C6: =C4-C5 -> -300 | D6: =D4-D5 -> -250 | E6: =E4-E5 -> -200 | F6: =F4-F5 -> -200 | G6: =G4-G5 -> -200 | H6: =H4-H5 -> -200 | I6: =I4-I5 -> -200 | J6: =J4-J5 -> -200 | ... N6: =N4-N5 -> -200
B7: VARIANCE (%) | C7: =IFERROR(C6/C5,0) -> -0.035294118 | D7: =IFERROR(D6/D5,0) -> -0.028735632 | E7: =IFERROR(E6/E5,0) -> -0.02247191 | F7: =IFERROR(F6/F5,0) -> -0.021505376 | G7: =IFERROR(G6/G5,0) -> -0.020833333 | H7: =IFERROR(H6/H5,0) -> -0.02 | I7: =IFERROR(I6/I5,0) -> -0.019230769 | J7: =IFERROR(J6/J5,0) -> -0.018518519 | ... N7: =IFERROR(N6/N5,0) -> -0.015873016
B8: FLAG | C8: =IF(ABS(C7)>0.05,"⚠ FLAG","OK") -> OK | D8: =IF(ABS(D7)>0.05,"⚠ FLAG","OK") -> OK | E8: =IF(ABS(E7)>0.05,"⚠ FLAG","OK") -> OK | F8: =IF(ABS(F7)>0.05,"⚠ FLAG","OK") -> OK | G8: =IF(ABS(G7)>0.05,"⚠ FLAG","OK") -> OK | H8: =IF(ABS(H7)>0.05,"⚠ FLAG","OK") -> OK | I8: =IF(ABS(I7)>0.05,"⚠ FLAG","OK") -> OK | J8: =IF(ABS(J7)>0.05,"⚠ FLAG","OK") -> OK | ... N8: =IF(ABS(N7)>0.05,"⚠ FLAG","OK") -> OK
A9: PHILIPPINES
B10: ACTUAL (SGD '000) | C10: ='Raw Data'!C5 -> 3100 | D10: ='Raw Data'!D5 -> 3200 | E10: ='Raw Data'!E5 -> 3350 | F10: ='Raw Data'!F5 -> 3500 | G10: ='Raw Data'!G5 -> 3650 | H10: ='Raw Data'!H5 -> 3800 | I10: ='Raw Data'!I5 -> 3950 | J10: ='Raw Data'!J5 -> 4100 | ... N10: ='Raw Data'!N5 -> 4900
B11: BUDGET (SGD '000) | C11: 3200 | D11: 3300 | E11: 3450 | F11: 3600 | G11: 3750 | H11: 3900 | I11: 4050 | J11: 4200 | K11: 4400 | L11: 4600 | M11: 4800 | N11: 5000
B12: VARIANCE (SGD '000) | C12: =C10-C11 -> -100 | D12: =D10-D11 -> -100 | E12: =E10-E11 -> -100 | F12: =F10-F11 -> -100 | G12: =G10-G11 -> -100 | H12: =H10-H11 -> -100 | I12: =I10-I11 -> -100 | J12: =J10-J11 -> -100 | ... N12: =N10-N11 -> -100
B13: VARIANCE (%) | C13: =IFERROR(C12/C11,0) -> -0.03125 | D13: =IFERROR(D12/D11,0) -> -0.03030303 | E13: =IFERROR(E12/E11,0) -> -0.028985507 | F13: =IFERROR(F12/F11,0) -> -0.027777778 | G13: =IFERROR(G12/G11,0) -> -0.026666667 | H13: =IFERROR(H12/H11,0) -> -0.025641026 | I13: =IFERROR(I12/I11,0) -> -0.024691358 | J13: =IFERROR(J12/J11,0) -> -0.023809524 | ... N13: =IFERROR(N12/N11,0) -> -0.02
B14: FLAG | C14: =IF(ABS(C13)>0.05,"⚠ FLAG","OK") -> OK | D14: =IF(ABS(D13)>0.05,"⚠ FLAG","OK") -> OK | E14: =IF(ABS(E13)>0.05,"⚠ FLAG","OK") -> OK | F14: =IF(ABS(F13)>0.05,"⚠ FLAG","OK") -> OK | G14: =IF(ABS(G13)>0.05,"⚠ FLAG","OK") -> OK | H14: =IF(ABS(H13)>0.05,"⚠ FLAG","OK") -> OK | I14: =IF(ABS(I13)>0.05,"⚠ FLAG","OK") -> OK | J14: =IF(ABS(J13)>0.05,"⚠ FLAG","OK") -> OK | ... N14: =IF(ABS(N13)>0.05,"⚠ FLAG","OK") -> OK
A15: VIETNAM
B16: ACTUAL (SGD '000) | C16: ='Raw Data'!C6 -> 1800 | D16: ='Raw Data'!D6 -> 1850 | E16: ='Raw Data'!E6 -> 2000 | F16: ='Raw Data'!F6 -> 2000 | G16: ='Raw Data'!G6 -> 2100 | H16: ='Raw Data'!H6 -> 2200 | I16: ='Raw Data'!I6 -> 2300 | J16: ='Raw Data'!J6 -> 2400 | ... N16: ='Raw Data'!N6 -> 2850
B17: BUDGET (SGD '000) | C17: 1850 | D17: 1900 | E17: 1970 | F17: 2050 | G17: 2150 | H17: 2250 | I17: 2350 | J17: 2450 | K17: 2550 | L17: 2650 | M17: 2750 | N17: 2900
B18: VARIANCE (SGD '000) | C18: =C16-C17 -> -50 | D18: =D16-D17 -> -50 | E18: =E16-E17 -> 30 | F18: =F16-F17 -> -50 | G18: =G16-G17 -> -50 | H18: =H16-H17 -> -50 | I18: =I16-I17 -> -50 | J18: =J16-J17 -> -50 | ... N18: =N16-N17 -> -50
B19: VARIANCE (%) | C19: =IFERROR(C18/C17,0) -> -0.027027027 | D19: =IFERROR(D18/D17,0) -> -0.026315789 | E19: =IFERROR(E18/E17,0) -> 0.015228426 | F19: =IFERROR(F18/F17,0) -> -0.024390244 | G19: =IFERROR(G18/G17,0) -> -0.023255814 | H19: =IFERROR(H18/H17,0) -> -0.022222222 | I19: =IFERROR(I18/I17,0) -> -0.021276596 | J19: =IFERROR(J18/J17,0) -> -0.020408163 | ... N19: =IFERROR(N18/N17,0) -> -0.017241379
B20: FLAG | C20: =IF(ABS(C19)>0.05,"⚠ FLAG","OK") -> OK | D20: =IF(ABS(D19)>0.05,"⚠ FLAG","OK") -> OK | E20: =IF(ABS(E19)>0.05,"⚠ FLAG","OK") -> OK | F20: =IF(ABS(F19)>0.05,"⚠ FLAG","OK") -> OK | G20: =IF(ABS(G19)>0.05,"⚠ FLAG","OK") -> OK | H20: =IF(ABS(H19)>0.05,"⚠ FLAG","OK") -> OK | I20: =IF(ABS(I19)>0.05,"⚠ FLAG","OK") -> OK | J20: =IF(ABS(J19)>0.05,"⚠ FLAG","OK") -> OK | ... N20: =IF(ABS(N19)>0.05,"⚠ FLAG","OK") -> OK

Sheet KPI Dashboard
A1: KPI DASHBOARD - MONEE BANKING SEGMENT | FY2025
A2: KPI | B2: MARKET | C2: 45658 | D2: 45689 | E2: 45717 | F2: 45748 | G2: 45778 | H2: 45809 | I2: 45839 | J2: 45870 | K2: 45901 | L2: 45931 | M2: 45962 | N2: 45992
A3: KPI 1 - REVENUE MoM GROWTH (%)
B4: INDONESIA | C4: - | D4: =IFERROR(('Raw Data'!D4-'Raw Data'!C4)/'Raw Data'!C4,0) -> 0.030487805 | E4: =IFERROR(('Raw Data'!E4-'Raw Data'!D4)/'Raw Data'!D4,0) -> 0.029585799 | F4: =IFERROR(('Raw Data'!F4-'Raw Data'!E4)/'Raw Data'!E4,0) -> 0.045977011 | G4: =IFERROR(('Raw Data'!G4-'Raw Data'!F4)/'Raw Data'!F4,0) -> 0.032967033 | H4: =IFERROR(('Raw Data'!H4-'Raw Data'!G4)/'Raw Data'!G4,0) -> 0.042553191 | I4: =IFERROR(('Raw Data'!I4-'Raw Data'!H4)/'Raw Data'!H4,0) -> 0.040816327 | J4: =IFERROR(('Raw Data'!J4-'Raw Data'!I4)/'Raw Data'!I4,0) -> 0.039215686 | K4: =IFERROR(('Raw Data'!K4-'Raw Data'!J4)/'Raw Data'!J4,0) -> 0.037735849 | ... N4: =IFERROR(('Raw Data'!N4-'Raw Data'!M4)/'Raw Data'!M4,0) -> 0.042016807
B5: PHILIPPINES | C5: - | D5: =IFERROR(('Raw Data'!D5-'Raw Data'!C5)/'Raw Data'!C5,0) -> 0.032258065 | E5: =IFERROR(('Raw Data'!E5-'Raw Data'!D5)/'Raw Data'!D5,0) -> 0.046875 | F5: =IFERROR(('Raw Data'!F5-'Raw Data'!E5)/'Raw Data'!E5,0) -> 0.044776119 | G5: =IFERROR(('Raw Data'!G5-'Raw Data'!F5)/'Raw Data'!F5,0) -> 0.042857143 | H5: =IFERROR(('Raw Data'!H5-'Raw Data'!G5)/'Raw Data'!G5,0) -> 0.04109589 | I5: =IFERROR(('Raw Data'!I5-'Raw Data'!H5)/'Raw Data'!H5,0) -> 0.039473684 | J5: =IFERROR(('Raw Data'!J5-'Raw Data'!I5)/'Raw Data'!I5,0) -> 0.037974684 | K5: =IFERROR(('Raw Data'!K5-'Raw Data'!J5)/'Raw Data'!J5,0) -> 0.048780488 | ... N5: =IFERROR(('Raw Data'!N5-'Raw Data'!M5)/'Raw Data'!M5,0) -> 0.042553191
B6: VIETNAM | C6: - | D6: =IFERROR(('Raw Data'!D6-'Raw Data'!C6)/'Raw Data'!C6,0) -> 0.027777778 | E6: =IFERROR(('Raw Data'!E6-'Raw Data'!D6)/'Raw Data'!D6,0) -> 0.081081081 | F6: =IFERROR(('Raw Data'!F6-'Raw Data'!E6)/'Raw Data'!E6,0) -> 0 | G6: =IFERROR(('Raw Data'!G6-'Raw Data'!F6)/'Raw Data'!F6,0) -> 0.05 | H6: =IFERROR(('Raw Data'!H6-'Raw Data'!G6)/'Raw Data'!G6,0) -> 0.047619048 | I6: =IFERROR(('Raw Data'!I6-'Raw Data'!H6)/'Raw Data'!H6,0) -> 0.045454545 | J6: =IFERROR(('Raw Data'!J6-'Raw Data'!I6)/'Raw Data'!I6,0) -> 0.043478261 | K6: =IFERROR(('Raw Data'!K6-'Raw Data'!J6)/'Raw Data'!J6,0) -> 0.041666667 | ... N6: =IFERROR(('Raw Data'!N6-'Raw Data'!M6)/'Raw Data'!M6,0) -> 0.055555556
B7: TOTAL | C7: - | D7: =IFERROR(('Raw Data'!D7-'Raw Data'!C7)/'Raw Data'!C7,0) -> 0.030534351 | E7: =IFERROR(('Raw Data'!E7-'Raw Data'!D7)/'Raw Data'!D7,0) -> 0.040740741 | F7: =IFERROR(('Raw Data'!F7-'Raw Data'!E7)/'Raw Data'!E7,0) -> 0.039145907 | G7: =IFERROR(('Raw Data'!G7-'Raw Data'!F7)/'Raw Data'!F7,0) -> 0.037671233 | H7: =IFERROR(('Raw Data'!H7-'Raw Data'!G7)/'Raw Data'!G7,0) -> 0.04290429 | I7: =IFERROR(('Raw Data'!I7-'Raw Data'!H7)/'Raw Data'!H7,0) -> 0.041139241 | J7: =IFERROR(('Raw Data'!J7-'Raw Data'!I7)/'Raw Data'!I7,0) -> 0.039513678 | K7: =IFERROR(('Raw Data'!K7-'Raw Data'!J7)/'Raw Data'!J7,0) -> 0.040935673 | ... N7: =IFERROR(('Raw Data'!N7-'Raw Data'!M7)/'Raw Data'!M7,0) -> 0.044041451
A8: KPI 2 - COST-TO-INCOME-RATIO
B9: INDONESIA | C9: =IFERROR('Raw Data'!C9/'Raw Data'!C4,0) -> 0.64634146 | D9: =IFERROR('Raw Data'!D9/'Raw Data'!D4,0) -> 0.63905325 | E9: =IFERROR('Raw Data'!E9/'Raw Data'!E4,0) -> 0.63218391 | F9: =IFERROR('Raw Data'!F9/'Raw Data'!F4,0) -> 0.62637363 | G9: =IFERROR('Raw Data'!G9/'Raw Data'!G4,0) -> 0.61702128 | H9: =IFERROR('Raw Data'!H9/'Raw Data'!H4,0) -> 0.6122449 | I9: =IFERROR('Raw Data'!I9/'Raw Data'!I4,0) -> 0.60784314 | J9: =IFERROR('Raw Data'!J9/'Raw Data'!J4,0) -> 0.60377358 | ... N9: =IFERROR('Raw Data'!N9/'Raw Data'!N4,0) -> 0.56451613
B10: PHILIPPINES | C10: =IFERROR('Raw Data'!C10/'Raw Data'!C5,0) -> 0.67741935 | D10: =IFERROR('Raw Data'!D10/'Raw Data'!D5,0) -> 0.671875 | E10: =IFERROR('Raw Data'!E10/'Raw Data'!E5,0) -> 0.65671642 | F10: =IFERROR('Raw Data'!F10/'Raw Data'!F5,0) -> 0.65714286 | G10: =IFERROR('Raw Data'!G10/'Raw Data'!G5,0) -> 0.64383562 | H10: =IFERROR('Raw Data'!H10/'Raw Data'!H5,0) -> 0.64473684 | I10: =IFERROR('Raw Data'!I10/'Raw Data'!I5,0) -> 0.63291139 | J10: =IFERROR('Raw Data'!J10/'Raw Data'!J5,0) -> 0.63414634 | ... N10: =IFERROR('Raw Data'!N10/'Raw Data'!N5,0) -> 0.6122449
B11: VIETNAM | C11: =IFERROR('Raw Data'!C11/'Raw Data'!C6,0) -> 0.72222222 | D11: =IFERROR('Raw Data'!D11/'Raw Data'!D6,0) -> 0.71351351 | E11: =IFERROR('Raw Data'!E11/'Raw Data'!E6,0) -> 0.675 | F11: =IFERROR('Raw Data'!F11/'Raw Data'!F6,0) -> 0.7 | G11: =IFERROR('Raw Data'!G11/'Raw Data'!G6,0) -> 0.69047619 | H11: =IFERROR('Raw Data'!H11/'Raw Data'!H6,0) -> 0.68181818 | I11: =IFERROR('Raw Data'!I11/'Raw Data'!I6,0) -> 0.67391304 | J11: =IFERROR('Raw Data'!J11/'Raw Data'!J6,0) -> 0.66666667 | ... N11: =IFERROR('Raw Data'!N11/'Raw Data'!N6,0) -> 0.63859649
B12: TOTAL | C12: =IFERROR('Raw Data'!C12/'Raw Data'!C7,0) -> 0.66412214 | D12: =IFERROR('Raw Data'!D12/'Raw Data'!D7,0) -> 0.65703704 | E12: =IFERROR('Raw Data'!E12/'Raw Data'!E7,0) -> 0.64412811 | F12: =IFERROR('Raw Data'!F12/'Raw Data'!F7,0) -> 0.64383562 | G12: =IFERROR('Raw Data'!G12/'Raw Data'!G7,0) -> 0.63366337 | H12: =IFERROR('Raw Data'!H12/'Raw Data'!H7,0) -> 0.62974684 | I12: =IFERROR('Raw Data'!I12/'Raw Data'!I7,0) -> 0.6231003 | J12: =IFERROR('Raw Data'!J12/'Raw Data'!J7,0) -> 0.61988304 | ... N12: =IFERROR('Raw Data'!N12/'Raw Data'!N7,0) -> 0.5866005
A13: KPI 3 - NPL RATE
B14: INDONESIA | C14: ='Raw Data'!C18 -> 0.021 | D14: ='Raw Data'!D18 -> 0.02 | E14: ='Raw Data'!E18 -> 0.021 | F14: ='Raw Data'!F18 -> 0.022 | G14: ='Raw Data'!G18 -> 0.021 | H14: ='Raw Data'!H18 -> 0.02 | I14: ='Raw Data'!I18 -> 0.019 | J14: ='Raw Data'!J18 -> 0.019 | ... N14: ='Raw Data'!N18 -> 0.017
B15: PHILIPPINES | C15: ='Raw Data'!C19 -> 0.028 | D15: ='Raw Data'!D19 -> 0.027 | E15: ='Raw Data'!E19 -> 0.027 | F15: ='Raw Data'!F19 -> 0.026 | G15: ='Raw Data'!G19 -> 0.025 | H15: ='Raw Data'!H19 -> 0.025 | I15: ='Raw Data'!I19 -> 0.024 | J15: ='Raw Data'!J19 -> 0.024 | ... N15: ='Raw Data'!N19 -> 0.021
B16: VIETNAM | C16: ='Raw Data'!C20 -> 0.032 | D16: ='Raw Data'!D20 -> 0.031 | E16: ='Raw Data'!E20 -> 0.03 | F16: ='Raw Data'!F20 -> 0.03 | G16: ='Raw Data'!G20 -> 0.029 | H16: ='Raw Data'!H20 -> 0.028 | I16: ='Raw Data'!I20 -> 0.028 | J16: ='Raw Data'!J20 -> 0.028 | ... N16: ='Raw Data'!N20 -> 0.025
A17: KPI 4 - ACTIVE USER GROWTH MoM %
B18: INDONESIA | C18: - | D18: =IFERROR(('Raw Data'!D14-'Raw Data'!C14)/'Raw Data'!C14,0) -> 0.035714286 | E18: =IFERROR(('Raw Data'!E14-'Raw Data'!D14)/'Raw Data'!D14,0) -> 0.034482759 | F18: =IFERROR(('Raw Data'!F14-'Raw Data'!E14)/'Raw Data'!E14,0) -> 0.044444444 | G18: =IFERROR(('Raw Data'!G14-'Raw Data'!F14)/'Raw Data'!F14,0) -> 0.042553191 | H18: =IFERROR(('Raw Data'!H14-'Raw Data'!G14)/'Raw Data'!G14,0) -> 0.040816327 | I18: =IFERROR(('Raw Data'!I14-'Raw Data'!H14)/'Raw Data'!H14,0) -> 0.049019608 | J18: =IFERROR(('Raw Data'!J14-'Raw Data'!I14)/'Raw Data'!I14,0) -> 0.046728972 | K18: =IFERROR(('Raw Data'!K14-'Raw Data'!J14)/'Raw Data'!J14,0) -> 0.044642857 | ... N18: =IFERROR(('Raw Data'!N14-'Raw Data'!M14)/'Raw Data'!M14,0) -> 0.046875
B19: PHILIPPINES | C19: - | D19: =IFERROR(('Raw Data'!D15-'Raw Data'!C15)/'Raw Data'!C15,0) -> 0.037837838 | E19: =IFERROR(('Raw Data'!E15-'Raw Data'!D15)/'Raw Data'!D15,0) -> 0.041666667 | F19: =IFERROR(('Raw Data'!F15-'Raw Data'!E15)/'Raw Data'!E15,0) -> 0.05 | G19: =IFERROR(('Raw Data'!G15-'Raw Data'!F15)/'Raw Data'!F15,0) -> 0.047619048 | H19: =IFERROR(('Raw Data'!H15-'Raw Data'!G15)/'Raw Data'!G15,0) -> 0.045454545 | I19: =IFERROR(('Raw Data'!I15-'Raw Data'!H15)/'Raw Data'!H15,0) -> 0.052173913 | J19: =IFERROR(('Raw Data'!J15-'Raw Data'!I15)/'Raw Data'!I15,0) -> 0.053719008 | K19: =IFERROR(('Raw Data'!K15-'Raw Data'!J15)/'Raw Data'!J15,0) -> 0.050980392 | ... N19: =IFERROR(('Raw Data'!N15-'Raw Data'!M15)/'Raw Data'!M15,0) -> 0.053872054
B20: VIETNAM | C20: - | D20: =IFERROR(('Raw Data'!D16-'Raw Data'!C16)/'Raw Data'!C16,0) -> 0.030612245 | E20: =IFERROR(('Raw Data'!E16-'Raw Data'!D16)/'Raw Data'!D16,0) -> 0.03960396 | F20: =IFERROR(('Raw Data'!F16-'Raw Data'!E16)/'Raw Data'!E16,0) -> 0.047619048 | G20: =IFERROR(('Raw Data'!G16-'Raw Data'!F16)/'Raw Data'!F16,0) -> 0.054545455 | H20: =IFERROR(('Raw Data'!H16-'Raw Data'!G16)/'Raw Data'!G16,0) -> 0.051724138 | I20: =IFERROR(('Raw Data'!I16-'Raw Data'!H16)/'Raw Data'!H16,0) -> 0.057377049 | J20: =IFERROR(('Raw Data'!J16-'Raw Data'!I16)/'Raw Data'!I16,0) -> 0.054263566 | K20: =IFERROR(('Raw Data'!K16-'Raw Data'!J16)/'Raw Data'!J16,0) -> 0.058823529 | ... N20: =IFERROR(('Raw Data'!N16-'Raw Data'!M16)/'Raw Data'!M16,0) -> 0.055900621
A21: KPI 5 - REVENUE PER ACTIVE USER (SGD '000)
B22: INDONESIA | C22: =IFERROR('Raw Data'!C4/'Raw Data'!C14,0) -> 1.952381 | D22: =IFERROR('Raw Data'!D4/'Raw Data'!D14,0) -> 1.9425287 | E22: =IFERROR('Raw Data'!E4/'Raw Data'!E14,0) -> 1.9333333 | F22: =IFERROR('Raw Data'!F4/'Raw Data'!F14,0) -> 1.9361702 | G22: =IFERROR('Raw Data'!G4/'Raw Data'!G14,0) -> 1.9183673 | H22: =IFERROR('Raw Data'!H4/'Raw Data'!H14,0) -> 1.9215686 | I22: =IFERROR('Raw Data'!I4/'Raw Data'!I14,0) -> 1.9065421 | J22: =IFERROR('Raw Data'!J4/'Raw Data'!J14,0) -> 1.8928571 | ... N22: =IFERROR('Raw Data'!N4/'Raw Data'!N14,0) -> 1.8507463
B23: PHILIPPINES | C23: =IFERROR('Raw Data'!C5/'Raw Data'!C15,0) -> 1.6756757 | D23: =IFERROR('Raw Data'!D5/'Raw Data'!D15,0) -> 1.6666667 | E23: =IFERROR('Raw Data'!E5/'Raw Data'!E15,0) -> 1.675 | F23: =IFERROR('Raw Data'!F5/'Raw Data'!F15,0) -> 1.6666667 | G23: =IFERROR('Raw Data'!G5/'Raw Data'!G15,0) -> 1.6590909 | H23: =IFERROR('Raw Data'!H5/'Raw Data'!H15,0) -> 1.6521739 | I23: =IFERROR('Raw Data'!I5/'Raw Data'!I15,0) -> 1.6322314 | J23: =IFERROR('Raw Data'!J5/'Raw Data'!J15,0) -> 1.6078431 | ... N23: =IFERROR('Raw Data'!N5/'Raw Data'!N15,0) -> 1.5654952
B24: VIETNAM | C24: =IFERROR('Raw Data'!C6/'Raw Data'!C16,0) -> 1.8367347 | D24: =IFERROR('Raw Data'!D6/'Raw Data'!D16,0) -> 1.8316832 | E24: =IFERROR('Raw Data'!E6/'Raw Data'!E16,0) -> 1.9047619 | F24: =IFERROR('Raw Data'!F6/'Raw Data'!F16,0) -> 1.8181818 | G24: =IFERROR('Raw Data'!G6/'Raw Data'!G16,0) -> 1.8103448 | H24: =IFERROR('Raw Data'!H6/'Raw Data'!H16,0) -> 1.8032787 | I24: =IFERROR('Raw Data'!I6/'Raw Data'!I16,0) -> 1.7829457 | J24: =IFERROR('Raw Data'!J6/'Raw Data'!J16,0) -> 1.7647059 | ... N24: =IFERROR('Raw Data'!N6/'Raw Data'!N16,0) -> 1.6764706

Sheet Forecast Model
A1: FORECAST MODEL - 3-MONTH ROLLING FORECAST (OCT-DEC 2025) | MONEE BANKING SEGMENT
A2: Actuals: Jan-Sep 2025 (linked from Raw Data)|Forecast Oct -Dec 2025 using adjustable growth assumptions
A4: ASSUMPTIONS - Yellow cells:change these to model different scenarios
A5: Revenue Growth Rate - Indonesia | B5: 0.04
A6: Revenue Growth Rate- Philippines | B6: 0.042
A7: Revenue Growth Rate- Vietnam | B7: 0.05
A8: Cost Growth Rate- all markets | B8: 0.025
A9: User Growth Rate- Indonesia | B9: 0.045
A10: User Growth Rate- Philippines | B10: 0.05
A11: User Growth Rate- Vietnam | B11: 0.055
A13: FORECAST TABLE-REVENUE,COSTS & GROSS PROFIT (SGD '000)
A14: MARKET | B14: METRIC | C14: SEP-25(ACTUAL) | D14: OCT-25(F) | E14: NOV-25(F) | F14: DEC-25(F)
A15: INDONESIA | B15: Revenue (SGD '000) | C15: ='Raw Data'!K4 -> 11000 | D15: =C15*(1+$B$5) -> 11440 | E15: =D15*(1+$B$5) -> 11897.6 | F15: =E15*(1+$B$5) -> 12373.504
B16: Costs (SGD '000) | C16: ='Raw Data'!K9 -> 6500 | D16: =C16*(1+$B$8) -> 6662.5 | E16: =D16*(1+$B$8) -> 6829.0625 | F16: =E16*(1+$B$8) -> 6999.7891
B17: Gross Profit (SGD '000) | C17: =C15-C16 -> 4500 | D17: =D15-D16 -> 4777.5 | E17: =E15-E16 -> 5068.5375 | F17: =F15-F16 -> 5373.7149
A19: PHILIPPINES | B19: Revenue (SGD '000) | C19: ='Raw Data'!K5 -> 4300 | D19: =C19*(1+$B$6) -> 4480.6 | E19: =D19*(1+$B$6) -> 4668.7852 | F19: =E19*(1+$B$6) -> 4864.8742
B20: Costs (SGD '000) | C20: ='Raw Data'!K10 -> 2700 | D20: =C20*(1+$B$8) -> 2767.5 | E20: =D20*(1+$B$8) -> 2836.6875 | F20: =E20*(1+$B$8) -> 2907.6047
B21: Gross Profit (SGD '000) | C21: =C19-C20 -> 1600 | D21: =D19-D20 -> 1713.1 | E21: =E19-E20 -> 1832.0977 | F21: =F19-F20 -> 1957.2695
A23: VIETNAM | B23: Revenue (SGD '000) | C23: ='Raw Data'!K6 -> 2500 | D23: =C23*(1+$B$7) -> 2625 | E23: =D23*(1+$B$7) -> 2756.25 | F23: =E23*(1+$B$7) -> 2894.0625
B24: Costs (SGD '000) | C24: ='Raw Data'!K11 -> 1650 | D24: =C24*(1+$B$8) -> 1691.25 | E24: =D24*(1+$B$8) -> 1733.5312 | F24: =E24*(1+$B$8) -> 1776.8695
B25: Gross Profit (SGD '000) | C25: =C23-C24 -> 850 | D25: =D23-D24 -> 933.75 | E25: =E23-E24 -> 1022.7188 | F25: =F23-F24 -> 1117.193

Sheet Mgmt Summary
A1: MANAGEMENT REPORT - SEP-25 |MONEE BANKING SEGMENT | SEP-25
A2: Prepared by Financial Analyst-Banking Segment Distribution : Regional Finance Director,COO Office
A4: 1. HEADLINE P&L - SEPTEMBER 2025(SGD '000)
A5: METRIC | B5: INDONESIA | C5: PHILIPPINES | D5: VIETNAM | E5: TOTAL
A6: Revenue | B6: ='Raw Data'!K4 -> 11000 | C6: ='Raw Data'!K5 -> 4300 | D6: ='Raw Data'!K6 -> 2500 | E6: =B6+C6+D6 -> 17800
A7: Operating Costs | B7: ='Raw Data'!K9 -> 6500 | C7: ='Raw Data'!K10 -> 2700 | D7: ='Raw Data'!K11 -> 1650 | E7: =B7+C7+D7 -> 10850
A8: Gross Profit | B8: =B6-B7 -> 4500 | C8: =C6-C7 -> 1600 | D8: =D6-D7 -> 850 | E8: =E6-E7 -> 6950
A9: Gross Margin % | B9: =IFERROR(B8/B6,0) -> 0.40909091 | C9: =IFERROR(C8/C6,0) -> 0.37209302 | D9: =IFERROR(D8/D6,0) -> 0.34 | E9: =IFERROR(E8/E6,0) -> 0.39044944
A11: 2.KPI SCOREBOARD - SEPTEMBER 2025
A12: KPI | B12: INDONESIA | C12: PHILIPPINES | D12: VIETNAM | E12: TARGET
A13: Revenue MoM Growth | B13: ='KPI Dashboard'!K4 -> 0.037735849 | C13: ='KPI Dashboard'!K5 -> 0.048780488 | D13: ='KPI Dashboard'!K6 -> 0.041666667 | E13: 0.03
A14: Cost-to-Income Ratio | B14: ='KPI Dashboard'!K9 -> 0.59090909 | C14: ='KPI Dashboard'!K10 -> 0.62790698 | D14: ='KPI Dashboard'!K11 -> 0.66 | E14: 0.65
A15: NPL Rate | B15: ='KPI Dashboard'!K14 -> 0.019 | C15: ='KPI Dashboard'!K15 -> 0.023 | D15: ='KPI Dashboard'!K16 -> 0.027 | E15: 0.03
A16: Active Users ('000) | B16: ='Raw Data'!K14 -> 5850 | C16: ='Raw Data'!K15 -> 2680 | D16: ='Raw Data'!K16 -> 1440 | E16: GROWTH
A18: 3. FINANCE COMMENTARY - KEY OBSERVATIONS
A19: Revenue Performance | B19: All three markets delivered revenue above prior month. Indonesia remains the dominant market at 65% of total segment revenue. Vietnam showed the strongest MoM growth at 4.2%
A20: Cost Management | B20: Operating costs grew at a lower rate than revenue across all markets, resulting in margin improvement. Indonesia cost-to-income ratio improved to 59.1%,approaching the 55% long-term-target.
A21: Credit Quality | B21: NPL rates continue to trend downward across all markets,reflecting improved underwriting standards.Vietnam remains highest at 2.7% but is on a declining trajectory.
A22: User Growth | B22: Active user base reached 14,370 ('000)across three markets.Indonesia added approximately 250k users in September,the highest single-month addition in FY2025.
A23: Risks & Watch Items | B23: ⚠ Philippines revenue variance vs budget flagged.Vietnam NPL approaching 3%threshold-recommend close monitoring in Q4.
A25: 4. NEXT STEPS & ACTION ITEMS
A26: ACTION | B26: DESCRIPTION | E26: OWNER
A27: Budget Review | B27: Philippines team to provide revised Q4 revenue forecast by 15 Oct | E27: Finance Lead - PH
A28: NPL Deep-Dive | B28: Vietnam credit team to present NPL root cause analysis at Oct business review | E28: Risk & Finance - VN
A29: Oct Close | B29: Month-end close to be completed by Nov 7; variance analysis due 10 Nov | E29: Regional Finance
A30: Q4 Forecast Update | B30: Update forecast model assumptions following Oct actuals | E30: Banking Segment FP&A
